LICENSE
README.md
setup.cfg
setup.py
moonheim_sms/__init__.py
moonheim_sms/exceptions.py
moonheim_sms/moonheimsms.py
moonheim_sms.egg-info/PKG-INFO
moonheim_sms.egg-info/SOURCES.txt
moonheim_sms.egg-info/dependency_links.txt
moonheim_sms.egg-info/not-zip-safe
moonheim_sms.egg-info/requires.txt
moonheim_sms.egg-info/top_level.txt
moonheim_sms/models/__init__.py
moonheim_sms/models/profile.py
moonheim_sms/models/send.py