Metadata-Version: 2.1
Name: moonheim-sms
Version: 0.1.2.2
Summary: Асинхронный модуль для работы с Moonheim SMS API
Author: fafatypoty
Author-email: fafatypoty@proton.me
License: Apache License, Version 2.0, see LICENSE file
Project-URL: Telegram, https://t.me/fafatypoty_cloaca
Project-URL: Github, https://github.com/fafatypoty/moonheim-sms
Keywords: moonheim,moonheim api,asyncmoonheim,moonheim sms,moonheimsms
Classifier: Development Status :: 3 - Alpha
Classifier: Intended Audience :: Developers
Classifier: Topic :: Software Development :: Build Tools
Classifier: License :: OSI Approved :: Apache Software License
Classifier: Programming Language :: Python :: 3
Classifier: Programming Language :: Python :: 3.10
Classifier: Programming Language :: Python :: 3.11
Classifier: Programming Language :: Python :: 3.12
Requires-Python: >=3.7
License-File: LICENSE
Requires-Dist: setuptools
Requires-Dist: pydantic
Requires-Dist: aiohttp
